ana/__init__.py
ana/__main__.py
ana/train.py
automated_neural_adapter_ana-7.6.1.dist-info/licenses/LICENSE
automated_neural_adapter_ana-7.6.1.dist-info/METADATA
automated_neural_adapter_ana-7.6.1.dist-info/WHEEL
automated_neural_adapter_ana-7.6.1.dist-info/top_level.txt
automated_neural_adapter_ana-7.6.1.dist-info/RECORD
