Metadata-Version: 2.4
Name: automated_neural_adapter_ANA
Version: 7.6.1
Summary: Automated Neural Adapter (ANA)
Home-page: 
Author: Rudransh Joshi
Author-email: rudransh20septmber@gmail.com
Requires-Python: >=3.10
License-File: LICENSE
Requires-Dist: torch
Requires-Dist: transformers
Requires-Dist: datasets
Requires-Dist: peft
Requires-Dist: accelerate
Requires-Dist: bitsandbytes
Dynamic: author
Dynamic: author-email
Dynamic: license-file
Dynamic: requires-python
